xitzin/__init__.py
xitzin/application.py
xitzin/auth.py
xitzin/cgi.py
xitzin/exceptions.py
xitzin/middleware.py
xitzin/py.typed
xitzin/requests.py
xitzin/responses.py
xitzin/routing.py
xitzin/scgi.py
xitzin/sqlmodel.py
xitzin/tasks.py
xitzin/templating.py
xitzin/testing.py
xitzin-0.5.0.dist-info/WHEEL
xitzin-0.5.0.dist-info/METADATA
xitzin-0.5.0.dist-info/RECORD
