Metadata-Version: 2.3
Name: xitzin
Version: 0.5.0
Summary: A Gemini Application Framework
Keywords: gemini,protocol,framework,async,geminispace
Author: Alan Velasco
Author-email: Alan Velasco <alanvelasco.a@gmail.com>
License: MIT
Classifier: Development Status :: 4 - Beta
Classifier: Intended Audience :: Developers
Classifier: License :: OSI Approved :: MIT License
Classifier: Programming Language :: Python :: 3
Classifier: Programming Language :: Python :: 3.10
Classifier: Programming Language :: Python :: 3.11
Classifier: Programming Language :: Python :: 3.12
Classifier: Programming Language :: Python :: 3.13
Classifier: Topic :: Internet
Classifier: Topic :: Software Development :: Libraries :: Application Frameworks
Classifier: Typing :: Typed
Requires-Dist: jinja2>=3.1.0
Requires-Dist: nauyaca>=0.3.2
Requires-Dist: rich>=14.2.0
Requires-Dist: structlog>=25.5.0
Requires-Dist: typing-extensions>=4.15.0
Requires-Dist: sqlmodel>=0.0.22 ; extra == 'sqlmodel'
Requires-Dist: croniter>=1.0.0 ; extra == 'tasks'
Requires-Python: >=3.10
Project-URL: Homepage, https://github.com/alanbato/xitzin
Project-URL: Documentation, https://xitzin.readthedocs.io
Project-URL: Repository, https://github.com/alanbato/xitzin.git
Project-URL: Issues, https://github.com/alanbato/xitzin/issues
Project-URL: Changelog, https://xitzin.readthedocs.io/changelog/
Provides-Extra: sqlmodel
Provides-Extra: tasks
